geneticpotion/__init__.py
geneticpotion/potion.py
geneticpotion-0.1.0.dist-info/LICENSE
geneticpotion-0.1.0.dist-info/METADATA
geneticpotion-0.1.0.dist-info/WHEEL
geneticpotion-0.1.0.dist-info/top_level.txt
geneticpotion-0.1.0.dist-info/RECORD
