Metadata-Version: 2.1
Name: geneticpotion
Version: 0.1.0
Summary: Linear Classificator enhancer based on genetic algorithm
Home-page: https://github.com/comptech-winter-school/genetic-potioncraft
Author: Kosaretskiy E. Geraskin S. Svetova K. Shperling S. Valeriya Novikova V.
Author-email: megametagross@outlook.de
License: UNKNOWN
Project-URL: Bug Tracker, https://github.com/comptech-winter-school/genetic-potioncraft/issues
Platform: UNKNOWN
Classifier: Programming Language :: Python :: 3
Classifier: License :: OSI Approved :: MIT License
Classifier: Operating System :: OS Independent
Requires-Python: >=3.6
License-File: LICENSE
Requires-Dist: deap
Requires-Dist: geppy
Requires-Dist: numpy
Requires-Dist: pandas
Requires-Dist: python-math
Requires-Dist: scikit-learn
